spacy_conll/__init__.py
spacy_conll/formatter.py
spacy_conll/parser.py
spacy_conll/utils.py
spacy_conll/version.py
spacy_conll/cli/__init__.py
spacy_conll/cli/parse.py
spacy_conll-4.0.1.dist-info/LICENSE
spacy_conll-4.0.1.dist-info/METADATA
spacy_conll-4.0.1.dist-info/WHEEL
spacy_conll-4.0.1.dist-info/entry_points.txt
spacy_conll-4.0.1.dist-info/top_level.txt
spacy_conll-4.0.1.dist-info/RECORD
