Metadata-Version: 2.1
Name: spacy-conll
Version: 4.0.1
Summary: A custom pipeline component for spaCy that can convert any parsed Doc and its sentences into CoNLL-U format. Also provides a command line entry point.
Author-email: Bram Vanroy <bramvanroy@hotmail.com>
Maintainer-email: Bram Vanroy <bramvanroy@hotmail.com>
License: BSD 2-Clause License
Project-URL: homepage, https://github.com/BramVanroy/spacy_conll
Project-URL: documentation, https://github.com/BramVanroy/spacy_conll
Project-URL: issues, https://github.com/BramVanroy/spacy_conll/issues
Project-URL: repository, https://github.com/BramVanroy/spacy_conll.git
Keywords: conll,conllu,nlp,parsing,spacy,spacy-extension,spacy_stanza,spacy_udpipe,stanza,tagging,udpipe
Classifier: Development Status :: 5 - Production/Stable
Classifier: Intended Audience :: Developers
Classifier: Intended Audience :: Science/Research
Classifier: Operating System :: OS Independent
Classifier: Programming Language :: Python :: 3.8
Classifier: Programming Language :: Python :: 3.9
Classifier: Programming Language :: Python :: 3.10
Classifier: Programming Language :: Python :: 3.11
Classifier: Programming Language :: Python :: 3.12
Classifier: Topic :: Scientific/Engineering
Classifier: Topic :: Text Processing
Requires-Python: >=3.8
License-File: LICENSE
Requires-Dist: spacy >=3.0.1
Provides-Extra: all
Requires-Dist: spacy-conll[parsers,pd] ; extra == 'all'
Provides-Extra: dev
Requires-Dist: black ; extra == 'dev'
Requires-Dist: flake8 ; extra == 'dev'
Requires-Dist: isort ; extra == 'dev'
Requires-Dist: pygments ; extra == 'dev'
Requires-Dist: pytest ; extra == 'dev'
Requires-Dist: spacy-conll[all] ; extra == 'dev'
Provides-Extra: parsers
Requires-Dist: spacy-stanza >=1.0.0 ; extra == 'parsers'
Requires-Dist: spacy-udpipe >=1.0.0 ; extra == 'parsers'
Provides-Extra: pd
Requires-Dist: pandas ; extra == 'pd'
